mcp_server_rememberizer/__init__.py
mcp_server_rememberizer/server.py
mcp_server_rememberizer/utils.py
mseep_mcp_server_rememberizer-0.1.10.dist-info/licenses/LICENSE
mseep_mcp_server_rememberizer-0.1.10.dist-info/METADATA
mseep_mcp_server_rememberizer-0.1.10.dist-info/WHEEL
mseep_mcp_server_rememberizer-0.1.10.dist-info/entry_points.txt
mseep_mcp_server_rememberizer-0.1.10.dist-info/top_level.txt
mseep_mcp_server_rememberizer-0.1.10.dist-info/RECORD
